MANIFEST.in
README.md
setup.cfg
setup.py
metabolts/__init__.py
metabolts/_version.py
metabolts/episodic_batcher.py
metabolts/utils.py
metabolts.egg-info/PKG-INFO
metabolts.egg-info/SOURCES.txt
metabolts.egg-info/dependency_links.txt
metabolts.egg-info/requires.txt
metabolts.egg-info/top_level.txt
metabolts/__pycache__/__init__.cpython-37.pyc
metabolts/__pycache__/_version.cpython-37.pyc
metabolts/__pycache__/episodic_batcher.cpython-37.pyc
metabolts/__pycache__/utils.cpython-37.pyc
metabolts/algorithms/.DS_Store
metabolts/algorithms/__init__.py
metabolts/algorithms/lightning_anil.py
metabolts/algorithms/protonet.py
tests/__init__.py
tests/prototypical_classifier_test.py