Metadata-Version: 2.1
Name: metabolts
Version: 0.0.1
Summary: Description of my super metabolts.
Home-page: https://learnables.github.com/metabolts
Author: Seb Arnold
Author-email: smr.arnold@gmail.com
License: License :: OSI Approved :: Apache Software License
Download-URL: https://github.com/learnables/metabolts/archive/0.0.1.zip
Platform: UNKNOWN
